MANIFEST.in
README.rst
requirements.txt
setup.py
bin/funniest-joke
docs/1.txt
funniest_joke/__init__.py
funniest_joke/command_line.py
funniest_joke/joke.dat
funniest_joke/text.py
funniest_joke.egg-info/PKG-INFO
funniest_joke.egg-info/SOURCES.txt
funniest_joke.egg-info/dependency_links.txt
funniest_joke.egg-info/entry_points.txt
funniest_joke.egg-info/not-zip-safe
funniest_joke.egg-info/requires.txt
funniest_joke.egg-info/top_level.txt