Metadata-Version: 1.1
Name: funniest-joke
Version: 0.2
Summary: The funniest joke in the world.
Home-page: http://github.com/webee/funniest
Author: webee
Author-email: webee.yw@gmail.com
License: MIT
Keywords: funniest joke comedy flying circus
Platform: UNKNOWN
Classifier: Development Status :: 3 - Alpha
Classifier: License :: OSI Approved :: MIT License
Classifier: Programming Language :: Python :: 2.7
Classifier: Topic :: Text Processing :: Linguistic
